lazuli/__init__.py
lazuli/account.py
lazuli/character.py
lazuli/database.py
lazuli/inventory.py
lazuli/jobs.py
lazuli/jobs.yaml
lazuli/utility.py
lazuli-3.0.2.dist-info/LICENSE
lazuli-3.0.2.dist-info/METADATA
lazuli-3.0.2.dist-info/WHEEL
lazuli-3.0.2.dist-info/top_level.txt
lazuli-3.0.2.dist-info/RECORD
