Metadata-Version: 2.1
Name: lazuli
Version: 3.0.2
Summary: A Python-based tool for interacting with AzureMSv316-based databases.
Author: Amos Chua
Maintainer: Brandon Phu
License: AGPL-3.0 license
Project-URL: Homepage, https://github.com/TEAM-SPIRIT-Productions/Lazuli
Project-URL: Bug Tracker, https://github.com/TEAM-SPIRIT-Productions/Lazuli/issues
Project-URL: Wiki, https://github.com/TEAM-SPIRIT-Productions/Lazuli/wiki
Project-URL: API Docs, https://team-spirit-productions.github.io/Lazuli/
Keywords: database,maplestory
Classifier: Development Status :: 5 - Production/Stable
Classifier: Intended Audience :: Developers
Classifier: Intended Audience :: Education
Classifier: Operating System :: OS Independent
Classifier: License :: OSI Approved :: GNU Affero General Public License v3 or later (AGPLv3+)
Classifier: Natural Language :: English
Classifier: Programming Language :: Python :: 3.10
Classifier: Programming Language :: Python :: 3.11
Classifier: Topic :: Games/Entertainment :: Side-Scrolling/Arcade Games
Requires-Python: >=3.10.0
License-File: LICENSE
Requires-Dist: mysql-connector-python (>=8.0.30)
Requires-Dist: protobuf (<4.0.*,>=3.2.*)
Requires-Dist: ruamel.yaml (<18.0.0,>=0.17.21)
